wirl_pregel_runner/__init__.py
wirl_pregel_runner/pregel_graph_builder.py
wirl_pregel_runner/pregel_runner.py
wirl_pregel_runner-0.1.0.dist-info/METADATA
wirl_pregel_runner-0.1.0.dist-info/WHEEL
wirl_pregel_runner-0.1.0.dist-info/RECORD
