Metadata-Version: 2.4
Name: wirl-pregel-runner
Version: 0.1.0
Summary: Pregel-based runner for WIRL workflows
Project-URL: Repository, https://github.com/wirl/packages/wirl-pregel-runner
Author: Artem Goncharov
License: MIT
Requires-Python: >=3.10
Requires-Dist: langgraph==0.6.7
Requires-Dist: wirl-lang>=0.1.0
